agave_pyclient/__init__.py
agave_pyclient/agave.py
agave_pyclient/commandbuffer.py
agave_pyclient-1.8.1.dist-info/LICENSE
agave_pyclient-1.8.1.dist-info/METADATA
agave_pyclient-1.8.1.dist-info/WHEEL
agave_pyclient-1.8.1.dist-info/top_level.txt
agave_pyclient-1.8.1.dist-info/RECORD
