Metadata-Version: 2.1
Name: agave-pyclient
Version: 1.8.1
Summary: A Python client for the Agave 3d volume renderer
Home-page: https://github.com/allen-cell-animated/agave
Author: Daniel Toloudis
Author-email: danielt@alleninstitute.org
License: Allen Institute Software License
Keywords: agave_pyclient
Classifier: Development Status :: 5 - Production/Stable
Classifier: Environment :: GPU
Classifier: Intended Audience :: Education
Classifier: Intended Audience :: Developers
Classifier: Intended Audience :: Healthcare Industry
Classifier: Intended Audience :: Science/Research
Classifier: License :: Free for non-commercial use
Classifier: Natural Language :: English
Classifier: Programming Language :: Python :: 3.7
Classifier: Programming Language :: Python :: 3.8
Classifier: Programming Language :: Python :: 3.9
Classifier: Topic :: Multimedia :: Graphics :: 3D Rendering
Classifier: Topic :: Scientific/Engineering :: Visualization
Classifier: Topic :: Scientific/Engineering :: Medical Science Apps.
Classifier: Topic :: Scientific/Engineering :: Image Processing
Requires-Python: >=3.7
License-File: LICENSE
Requires-Dist: numpy
Requires-Dist: ws4py==0.5.1
Requires-Dist: Pillow==10.3.0
Provides-Extra: all
Requires-Dist: numpy; extra == "all"
Requires-Dist: ws4py==0.5.1; extra == "all"
Requires-Dist: Pillow==10.3.0; extra == "all"
Requires-Dist: pytest-runner>=5.2; extra == "all"
Requires-Dist: black>=19.10b0; extra == "all"
Requires-Dist: flake8>=3.8.3; extra == "all"
Requires-Dist: flake8-debugger>=3.2.1; extra == "all"
Requires-Dist: pytest>=5.4.3; extra == "all"
Requires-Dist: pytest-cov>=2.9.0; extra == "all"
Requires-Dist: pytest-raises>=0.11; extra == "all"
Requires-Dist: bump2version>=1.0.1; extra == "all"
Requires-Dist: coverage>=5.1; extra == "all"
Requires-Dist: ipython>=7.15.0; extra == "all"
Requires-Dist: m2r2>=0.2.7; extra == "all"
Requires-Dist: Sphinx>=3.4.3; extra == "all"
Requires-Dist: sphinx-rtd-theme>=0.5.1; extra == "all"
Requires-Dist: tox>=3.15.2; extra == "all"
Requires-Dist: twine>=3.1.1; extra == "all"
Requires-Dist: wheel>=0.34.2; extra == "all"
Provides-Extra: dev
Requires-Dist: pytest-runner>=5.2; extra == "dev"
Requires-Dist: black>=19.10b0; extra == "dev"
Requires-Dist: flake8>=3.8.3; extra == "dev"
Requires-Dist: flake8-debugger>=3.2.1; extra == "dev"
Requires-Dist: pytest>=5.4.3; extra == "dev"
Requires-Dist: pytest-cov>=2.9.0; extra == "dev"
Requires-Dist: pytest-raises>=0.11; extra == "dev"
Requires-Dist: bump2version>=1.0.1; extra == "dev"
Requires-Dist: coverage>=5.1; extra == "dev"
Requires-Dist: ipython>=7.15.0; extra == "dev"
Requires-Dist: m2r2>=0.2.7; extra == "dev"
Requires-Dist: Sphinx>=3.4.3; extra == "dev"
Requires-Dist: sphinx-rtd-theme>=0.5.1; extra == "dev"
Requires-Dist: tox>=3.15.2; extra == "dev"
Requires-Dist: twine>=3.1.1; extra == "dev"
Requires-Dist: wheel>=0.34.2; extra == "dev"
Provides-Extra: setup
Requires-Dist: pytest-runner>=5.2; extra == "setup"
Provides-Extra: test
Requires-Dist: black>=19.10b0; extra == "test"
Requires-Dist: flake8>=3.8.3; extra == "test"
Requires-Dist: flake8-debugger>=3.2.1; extra == "test"
Requires-Dist: pytest>=5.4.3; extra == "test"
Requires-Dist: pytest-cov>=2.9.0; extra == "test"
Requires-Dist: pytest-raises>=0.11; extra == "test"
